<beans xmlns="http://www.springframework.org/schema/beans"
	xmlns:xsi="http://www.w3.org/2001/XMLSchema-instance" xmlns:p="http://www.springframework.org/schema/p"
	xmlns:util="http://www.springframework.org/schema/util"
	xsi:schemaLocation="http://www.springframework.org/schema/beans
                    http://www.springframework.org/schema/beans/spring-beans-3.0.xsd
                    http://www.springframework.org/schema/util
                    http://www.springframework.org/schema/util/spring-util-3.0.xsd">

	<!-- example control -->
	<bean id="Uif-PasswordControl" parent="Uif-PasswordControl-parentBean" />
	<bean id="Uif-PasswordControl-parentBean" abstract="true"
		class="org.kuali.rice.contest.components.control.Password" scope="prototype"
		parent="Uif-ControlBase">
		<property name="template" value="/WEB-INF/ftl/components/control/password.ftl" />
		<property name="templateName" value="uif_password" />
		<property name="cssClasses">
			<list merge="true">
				<value>uif-password</value>
			</list>
		</property>
		<property name="size" value="30" />
	</bean>

    <!-- example widget -->
	<bean id="Uif-ColorPicker" parent="Uif-ColorPicker-parentBean" />
	<bean id="Uif-ColorPicker-parentBean" abstract="true"
		class="org.kuali.rice.contest.components.widget.ColorPicker" scope="prototype"
		parent="Uif-WidgetBase">
		<property name="template"
			value="/WEB-INF/ftl/components/widget/colorPicker.ftl" />
		<property name="templateName" value="uif_colorPicker" />
		<property name="defaultColor" value="#FFFFFF" />
		<property name="showColorPreviewIcon" value="true" />
	</bean>

    <!-- example control with widget -->
	<bean id="Uif-TextWithColorPickerControl" parent="Uif-TextWithColorPickerControl-parentBean" />
	<bean id="Uif-TextWithColorPickerControl-parentBean" abstract="true"
		class="org.kuali.rice.contest.components.control.TextWithColorPicker"
		scope="prototype" parent="Uif-TextControl">
		<property name="template"
			value="/WEB-INF/ftl/components/control/textWithColorPicker.ftl" />
		<property name="templateName" value="uif_textWithColorPicker" />
		<property name="size" value="7" />
		<property name="colorPicker">
			<bean parent="Uif-ColorPicker" />
		</property>
	</bean>



</beans>                    